polcurvefit/DataImport.py
polcurvefit/__init__.py
polcurvefit/forward.py
polcurvefit/polcurvefit.py
polcurvefit/data/example_nova.txt
polcurvefit/data/example_txt.txt
PolCurveFit-1.2.1.dist-info/METADATA
PolCurveFit-1.2.1.dist-info/WHEEL
PolCurveFit-1.2.1.dist-info/top_level.txt
PolCurveFit-1.2.1.dist-info/RECORD
