Metadata-Version: 2.1
Name: PolCurveFit
Version: 1.2.1
Summary: library for the analysis of polarization curves
Home-page: https://polcurvefit.readthedocs.io/
Author: Meeke van Ede
Author-email: meekevanede@gmail.com
License: MIT
Classifier: Intended Audience :: Developers
Classifier: License :: OSI Approved :: MIT License
Classifier: Programming Language :: Python
Classifier: Programming Language :: Python :: 3
Classifier: Programming Language :: Python :: 3.7
Classifier: Programming Language :: Python :: 3.8
Classifier: Programming Language :: Python :: 3.9
Classifier: Operating System :: OS Independent
Requires-Dist: numpy
Requires-Dist: scipy
Requires-Dist: matplotlib
Requires-Dist: pandas
